censorfix/__init__.py
censorfix/censorfix.py
censorfix/compile_stan.py
censorfix/test_censor.py
censor_fix-0.0.3.dist-info/LICENSE
censor_fix-0.0.3.dist-info/METADATA
censor_fix-0.0.3.dist-info/WHEEL
censor_fix-0.0.3.dist-info/top_level.txt
censor_fix-0.0.3.dist-info/RECORD
