Metadata-Version: 2.1
Name: censor-fix
Version: 0.0.3
Summary: A library for multiple imputation of censored data
Home-page: UNKNOWN
Author: Rowan Swiers
Author-email: rowan.swiers@astrazeneca.com
License: MIT
Platform: UNKNOWN
Requires-Python: >=3.5
Requires-Dist: numpy
Requires-Dist: pandas
Requires-Dist: joblib
Requires-Dist: tqdm
Requires-Dist: pystan
Requires-Dist: sklearn
